radmetric/__init__.py
radmetric/bert_score_worker.py
radmetric/bleu_worker.py
radmetric/rad_graph_worker.py
radmetric/rate_score_worker.py
radmetric/reward_server.py
radmetric/chexbert/__init__.py
radmetric/chexbert/f1chexbert.py
radmetric/chexbert/f1chexbert_worker.py
radmetric/semb_scorer/__init__.py
radmetric/semb_scorer/model.py
radmetric/semb_scorer/worker.py
rad_metric-0.1.4.dist-info/METADATA
rad_metric-0.1.4.dist-info/WHEEL
rad_metric-0.1.4.dist-info/top_level.txt
rad_metric-0.1.4.dist-info/RECORD
