Metadata-Version: 2.4
Name: rad-metric
Version: 0.1.4
Summary: Composite metrics for chest X-ray report (CXR) generation.
Author: Guanghui Qin
Project-URL: Homepage, https://github.com/hiaoxui/rad-metric
Classifier: Programming Language :: Python :: 3
Classifier: Operating System :: OS Independent
Requires-Python: >=3.9
Requires-Dist: torch>=2.1.0
Requires-Dist: numpy
Requires-Dist: transformers>=4.39.0
Requires-Dist: evaluate
Requires-Dist: bert-score
Requires-Dist: tqdm
Requires-Dist: ray
Requires-Dist: pandas
Requires-Dist: radgraph==0.1.18
Requires-Dist: RaTEScore==0.6.0
Requires-Dist: statsmodels==0.14.4
Requires-Dist: medspacy==1.3.1
